miner_ai_beta/loader/__init__.py
miner_ai_beta/loader/docs.py
miner_ai_beta/loader/excels.py
miner_ai_beta/loader/git.py
miner_ai_beta/loader/images.py
miner_ai_beta/loader/pdfs.py
miner_ai_beta/loader/ppts.py
miner_ai_beta/loader/tubes.py
miner_ai_beta/loader/union.py
miner_ai_beta/loader/web_pages.py
miner_ai_beta-0.1.21.dist-info/LICENSE
miner_ai_beta-0.1.21.dist-info/METADATA
miner_ai_beta-0.1.21.dist-info/WHEEL
miner_ai_beta-0.1.21.dist-info/RECORD
