Metadata-Version: 2.1
Name: miner-ai-beta
Version: 0.1.21
Summary: 
Home-page: https://github.com/Valerio357/miner-ai
License: MIT
Keywords: langchain,documents_mining,web_scraping
Author: Valerio Domenici
Author-email: valeriodomenici93@gmail.com
Requires-Python: >=3.11,<4.0
Classifier: License :: OSI Approved :: MIT License
Classifier: Programming Language :: Python :: 3
Classifier: Programming Language :: Python :: 3.11
Classifier: Programming Language :: Python :: 3.12
Requires-Dist: azure-ai-formrecognizer (>=3.3.3,<4.0.0)
Requires-Dist: bs4 (>=0.0.2,<0.0.3)
Requires-Dist: langchain (>=0.1.17,<0.2.0)
Requires-Dist: langchain-openai (>=0.1.6,<0.2.0)
Requires-Dist: openpyxl (>=3.1.2,<4.0.0)
Requires-Dist: pdfplumber (>=0.11.0,<0.12.0)
Requires-Dist: pillow (>=10.3.0,<11.0.0)
Requires-Dist: python-docx (>=1.1.2,<2.0.0)
Requires-Dist: python-pptx (>=0.6.23,<0.7.0)
Requires-Dist: pytube (>=15.0.0,<16.0.0)
Requires-Dist: selenium (>=4.20.0,<5.0.0)
Requires-Dist: tqdm (>=4.66.4,<5.0.0)
Requires-Dist: youtube-transcript-api (>=0.6.2,<0.7.0)
Project-URL: Repository, https://github.com/Valerio357/miner-ai
